harmony_gui/__init__.py
harmony_gui/gui.py
harmony_gui/gui_import/__init__.py
harmony_gui/gui_import/codeeditor.py
harmony_gui/gui_import/keywords.json
harmony_gui/gui_import/modules.json
harmony_gui/gui_import/tokens.json
harmony_gui-1.0.4.dist-info/METADATA
harmony_gui-1.0.4.dist-info/WHEEL
harmony_gui-1.0.4.dist-info/entry_points.txt
harmony_gui-1.0.4.dist-info/top_level.txt
harmony_gui-1.0.4.dist-info/RECORD
